pypitch-2.0.dist-info/WHEEL
pypitch-2.0.dist-info/METADATA
pypitch-2.0.dist-info/RECORD
pypitch-2.0.dist-info/top_level.txt
pypitch-2.0.dist-info/LICENSE
pypitch/__init__.py
pypitch/pypitch.pypy39-pp73-x86-linux-gnu.so
