Metadata-Version: 2.1
Name: pypitch
Version: 2.0
Summary: PyPitch analyses audio streams for pitch
Home-page: https://fofix.org
Author: FoFiX team
Author-email: contact@fofix.org
License: GPLv2+
Project-URL: Documentation, https://pypitch.readthedocs.io
Project-URL: Source Code, https://github.com/fofix/python-pypitch
Project-URL: Bug Tracker, https://github.com/fofix/python-pypitch/issues
Keywords: pitch audio
Classifier: Intended Audience :: Developers
Classifier: License :: OSI Approved :: GNU General Public License v2 or later (GPLv2+)
Classifier: Programming Language :: C++
Classifier: Programming Language :: Cython
Classifier: Programming Language :: Python
Classifier: Programming Language :: Python :: 2
Classifier: Programming Language :: Python :: 2.7
Classifier: Programming Language :: Python :: 3
Classifier: Programming Language :: Python :: 3.7
Classifier: Programming Language :: Python :: 3.8
Classifier: Programming Language :: Python :: 3.9
Classifier: Programming Language :: Python :: 3.10
Classifier: Programming Language :: Python :: 3.11
Classifier: Topic :: Multimedia
Classifier: Topic :: Multimedia :: Sound/Audio
Classifier: Topic :: Software Development :: Libraries
License-File: LICENSE
Requires-Dist: Cython (>=0.27)
Provides-Extra: docs
Requires-Dist: sphinx ; extra == 'docs'
Requires-Dist: sphinx-rtd-theme ; extra == 'docs'
Provides-Extra: tests
Requires-Dist: pytest (<5) ; (python_version < "3.4") and extra == 'tests'
Requires-Dist: numpy (<1.17) ; (python_version < "3.4") and extra == 'tests'
Requires-Dist: numpy (<1.22) ; (python_version == "3.7") and extra == 'tests'
Requires-Dist: pytest ; (python_version > "3.4") and extra == 'tests'
Requires-Dist: numpy ; (python_version > "3.7") and extra == 'tests'
